pp_paths/Tree.py
pp_paths/__init__.py
pp_paths/main.py
pp_paths/utils.py
pp_paths-1.0.1.dist-info/METADATA
pp_paths-1.0.1.dist-info/WHEEL
pp_paths-1.0.1.dist-info/entry_points.txt
pp_paths-1.0.1.dist-info/top_level.txt
pp_paths-1.0.1.dist-info/RECORD
