Metadata-Version: 2.1
Name: pp-paths
Version: 1.0.1
Summary: A python program to pretty print directory structures
Home-page: https://github.com/amokfa/pp_paths
Author: Sagar Tiwari
Author-email: iaansagar@gmail.com
